README.rst
setup.py
testinlabel/TLA.py
testinlabel/__init__.py
testinlabel/exportAbstract.py
testinlabel/request.py
testinlabel.egg-info/PKG-INFO
testinlabel.egg-info/SOURCES.txt
testinlabel.egg-info/dependency_links.txt
testinlabel.egg-info/entry_points.txt
testinlabel.egg-info/requires.txt
testinlabel.egg-info/top_level.txt
testinlabel/cli/__init__.py
testinlabel/cli/account.py
testinlabel/cli/run.py