Metadata-Version: 2.1
Name: testinlabel
Version: 0.0.10
Summary: 云测数据 标注平台pythonSDK
Home-page: http://ai.testin.cn/
Author: hide-in-code
Author-email: hejinlong@testin.cn
License: MIT Licence
Keywords: 云测,数据集,yuncedata,testin,testinlabel
Platform: any
